ntwork/__init__.py
ntwork/conf/__init__.py
ntwork/const/__init__.py
ntwork/const/notify_type.py
ntwork/const/send_type.py
ntwork/core/__init__.py
ntwork/core/mgr.py
ntwork/core/wework.py
ntwork/exception/__init__.py
ntwork/utils/__init__.py
ntwork/utils/logger.py
ntwork/utils/singleton.py
ntwork/utils/xdg.py
ntwork/wc/__init__.py
ntwork/wc/helper_4.0.8.6027.dat
ntwork/wc/wcprobe.cp38-win_amd64.pyd
ntwork-0.1.3.dist-info/LICENSE
ntwork-0.1.3.dist-info/METADATA
ntwork-0.1.3.dist-info/WHEEL
ntwork-0.1.3.dist-info/top_level.txt
ntwork-0.1.3.dist-info/RECORD
