Metadata-Version: 2.1
Name: ntwork
Version: 0.1.3
Summary: About Conversational RPA SDK for Chatbot Makers
Home-page: https://github.com/smallevilbeast/ntwork
Author: evilbeast
Author-email: 784615627@qq.com
License: MIT
Keywords: wework ntwork pywework rebot
Classifier: Development Status :: 4 - Beta
Classifier: License :: OSI Approved :: MIT License
Classifier: Programming Language :: Python :: 3.6
Classifier: Programming Language :: Python :: 3.7
Classifier: Programming Language :: Python :: 3.8
Classifier: Programming Language :: Python :: 3.9
Classifier: Programming Language :: Python :: 3.10
License-File: LICENSE
Requires-Dist: pyee
Requires-Dist: xcgui
